blueink/__init__.py
blueink/bundle_helper.py
blueink/client.py
blueink/constants.py
blueink/endpoints.py
blueink/paginator.py
blueink/person_helper.py
blueink/request_helper.py
blueink/model/__init__.py
blueink/model/bundles.py
blueink/model/persons.py
blueink/model/webhook.py
blueink/subclients/__init__.py
blueink/subclients/bundle.py
blueink/subclients/packet.py
blueink/subclients/person.py
blueink/subclients/subclient.py
blueink/subclients/template.py
blueink/subclients/webhook.py
blueink/tests/__init__.py
blueink/tests/test_bundle_helper.py
blueink/tests/test_client.py
blueink/tests/test_person_helper.py
blueink/utils/__init__.py
blueink/utils/testcase.py
blueink_client_python-1.0.0.dist-info/LICENSE
blueink_client_python-1.0.0.dist-info/METADATA
blueink_client_python-1.0.0.dist-info/WHEEL
blueink_client_python-1.0.0.dist-info/top_level.txt
blueink_client_python-1.0.0.dist-info/RECORD
