Metadata-Version: 2.1
Name: blueink-client-python
Version: 1.0.0
Summary: Python Client for Blueink eSignature API
Home-page: https://github.com/blueinkhq/blueink-client-python
Author: Blueink
Author-email: pypi@blueink.com
Project-URL: Bug Tracker, https://github.com/blueinkhq/blueink-client-python/issues
Classifier: Programming Language :: Python :: 3
Classifier: License :: OSI Approved :: MIT License
Classifier: Operating System :: OS Independent
Requires-Python: >=3.8
License-File: LICENSE
Requires-Dist: munch
Requires-Dist: requests
Requires-Dist: pydantic
Requires-Dist: email-validator
Provides-Extra: email-validator_
Requires-Dist: 1.2 ; extra == 'email-validator_'
Provides-Extra: munch
Requires-Dist: munch >=2.5 ; extra == 'munch'
Provides-Extra: pydantic
Requires-Dist: pydantic >=1.9 ; extra == 'pydantic'
Provides-Extra: requests
Requires-Dist: requests >=2.27 ; extra == 'requests'
